fyaml/__init__.py
fyaml/__main__.py
fyaml/fyaml.py
qyaml/__init__.py
qyaml/__main__.py
qyaml/qyaml.py
qyaml_smartptr-0.0.2.dist-info/LICENSE
qyaml_smartptr-0.0.2.dist-info/METADATA
qyaml_smartptr-0.0.2.dist-info/WHEEL
qyaml_smartptr-0.0.2.dist-info/entry_points.txt
qyaml_smartptr-0.0.2.dist-info/top_level.txt
qyaml_smartptr-0.0.2.dist-info/RECORD
