Metadata-Version: 2.1
Name: qyaml-smartptr
Version: 0.0.2
Summary: YAML query utility
Home-page: https://github.com/0x656b694d/qyaml
Author: Michaël Petrov
Author-email: smartptr@gmail.com
License: UNKNOWN
Project-URL: Bug Tracker, https://github.com/0x656b694d/qyaml/issues
Platform: UNKNOWN
Classifier: Programming Language :: Python :: 3
Classifier: License :: OSI Approved :: MIT License
Classifier: Operating System :: OS Independent
Requires-Python: <4,>=3.6
License-File: LICENSE
Requires-Dist: PyYAML
Provides-Extra: testing
Requires-Dist: PyYAML ; extra == 'testing'
